grid_df/__init__.py
grid_df/grid_df.py
grid_df-0.1.2.dist-info/METADATA
grid_df-0.1.2.dist-info/WHEEL
grid_df-0.1.2.dist-info/licenses/LICENSE
grid_df-0.1.2.dist-info/RECORD
