Metadata-Version: 2.3
Name: grid_df
Version: 0.1.2
Author-email: Vince Buffalo <vsbuffalo@gmail.com>
License-File: LICENSE
Requires-Python: >=3.12
Requires-Dist: numpy>=2.1.3
Requires-Dist: polars>=1.12.0
